rtl/core/defines.v
 /*                                                                      
 Copyright 2019 Blue Liang, liangkangnan@163.com
                                                                         
 Licensed under the Apache License, Version 2.0 (the "License");         
 you may not use this file except in compliance with the License.        
 You may obtain a copy of the License at                                 
                                                                         
     http://www.apache.org/licenses/LICENSE-2.0                          
                                                                         
 Unless required by applicable law or agreed to in writing, software    
 distributed under the License is distributed on an "AS IS" BASIS,       
 WITHOUT WARRANTIES OR CONDITIONS OF ANY KIND, either express or implied.
 See the License for the specific language governing permissions and     
 limitations under the License.                                          
 */

`define CpuResetAddr 32'h0

`define RstEnable 1'b0
`define RstDisable 1'b1
`define ZeroWord 32'h0
`define ZeroReg 5'h0
`define WriteEnable 1'b1
`define WriteDisable 1'b0
`define ReadEnable 1'b1
`define ReadDisable 1'b0
`define True 1'b1
`define False 1'b0
`define ChipEnable 1'b1
`define ChipDisable 1'b0
`define JumpEnable 1'b1
`define JumpDisable 1'b0
`define DivResultNotReady 1'b0
`define DivResultReady 1'b1
`define DivStart 1'b1
`define DivStop 1'b0
`define HoldEnable 1'b1
`define HoldDisable 1'b0
`define Stop 1'b1
`define NoStop 1'b0
`define RIB_ACK 1'b1
`define RIB_NACK 1'b0
`define RIB_REQ 1'b1
`define RIB_NREQ 1'b0
`define INT_ASSERT 1'b1
`define INT_DEASSERT 1'b0

`define INT_BUS 7:0
`define INT_NONE 8'h0
`define INT_RET 8'hff
`define INT_TIMER0 8'b00000001
`define INT_TIMER0_ENTRY_ADDR 32'h4

`define Hold_Flag_Bus   2:0
`define Hold_None 3'b000
`define Hold_Pc   3'b001
`define Hold_If   3'b010
`define Hold_Id   3'b011

// I type inst
`define INST_TYPE_I 7'b0010011
`define INST_ADDI   3'b000
`define INST_SLTI   3'b010
`define INST_SLTIU  3'b011
`define INST_XORI   3'b100
`define INST_ORI    3'b110
`define INST_ANDI   3'b111
`define INST_SLLI   3'b001
`define INST_SRI    3'b101

// L type inst
`define INST_TYPE_L 7'b0000011
`define INST_LB     3'b000
`define INST_LH     3'b001
`define INST_LW     3'b010
`define INST_LBU    3'b100
`define INST_LHU    3'b101

// S type inst
`define INST_TYPE_S 7'b0100011
`define INST_SB     3'b000
`define INST_SH     3'b001
`define INST_SW     3'b010

// R and M type inst
`define INST_TYPE_R_M 7'b0110011
// R type inst
`define INST_ADD_SUB 3'b000
`define INST_SLL    3'b001
`define INST_SLT    3'b010
`define INST_SLTU   3'b011
`define INST_XOR    3'b100
`define INST_SR     3'b101
`define INST_OR     3'b110
`define INST_AND    3'b111
// M type inst
`define INST_MUL    3'b000
`define INST_MULH   3'b001
`define INST_MULHSU 3'b010
`define INST_MULHU  3'b011
`define INST_DIV    3'b100
`define INST_DIVU   3'b101
`define INST_REM    3'b110
`define INST_REMU   3'b111

// J type inst
`define INST_JAL    7'b1101111
`define INST_JALR   7'b1100111

`define INST_LUI    7'b0110111
`define INST_AUIPC  7'b0010111
`define INST_NOP    32'h00000001
`define INST_NOP_OP 7'b0000001
`define INST_MRET   32'h30200073
`define INST_RET    32'h00008067

`define INST_FENCE  7'b0001111
`define INST_ECALL  32'h73
`define INST_EBREAK 32'h00100073

// J type inst
`define INST_TYPE_B 7'b1100011
`define INST_BEQ    3'b000
`define INST_BNE    3'b001
`define INST_BLT    3'b100
`define INST_BGE    3'b101
`define INST_BLTU   3'b110
`define INST_BGEU   3'b111

// CSR inst
`define INST_CSR    7'b1110011
`define INST_CSRRW  3'b001
`define INST_CSRRS  3'b010
`define INST_CSRRC  3'b011
`define INST_CSRRWI 3'b101
`define INST_CSRRSI 3'b110
`define INST_CSRRCI 3'b111

// CSR reg addr
`define CSR_CYCLE   12'hc00
`define CSR_CYCLEH  12'hc80
`define CSR_MTVEC   12'h305
`define CSR_MCAUSE  12'h342
`define CSR_MEPC    12'h341
`define CSR_MIE     12'h304
`define CSR_MSTATUS 12'h300
`define CSR_MSCRATCH 12'h340

`define RomNum 4096  // rom depth(how many words)

`define MemNum 4096  // memory depth(how many words)
`define MemBus 31:0
`define MemAddrBus 31:0

`define InstBus 31:0
`define InstAddrBus 31:0

// common regs
`define RegAddrBus 4:0
`define RegBus 31:0
`define DoubleRegBus 63:0
`define RegWidth 32
`define RegNum 32        // reg num
`define RegNumLog2 5


//
`define Sha1In 31:0
`define Sha1Out 159:0
`define Sha1Pad 512:0

rtl/core/sha1_dfa.v
`include "defines.v"


module sha1_dfa(

    input wire clk,
    input wire rst,

    // from ex
    input wire[`Sha1In] para_i,             // sha1输入
    input wire start_i,                     // 开始信号，运算期间这个信号需要一直保持有效
    input wire[`MemAddrBus] sha1_addr_i,    // 结果要写入的地址   

    // to ex
    output reg[`Sha1Out] result_o,          // sha1结果
    output reg ready_o,                     // 运算结束信号
    output reg busy_o,                      // 正在运算信号
    output reg[`MemAddrBus] sha1_addr_o  

    );

    // 状态定义
    localparam STATE_IDLE  = 4'b0001;
    localparam STATE_START = 4'b0010;
    localparam STATE_CALC  = 4'b0100;
    localparam STATE_END   = 4'b1000;

    reg[3:0] state;
    reg[`Sha1In] para;

    reg [`Sha1Pad] sha_pad;

    reg[511:0] W;
    wire[31:0] W_tmp;
    reg[31:0] A;
    reg[31:0] B;
    reg[31:0] C;
    reg[31:0] D;
    reg[31:0] E;
    reg[31:0] count;
    wire[31:0] fun_res;
    wire[31:0] k_res;
    
    assign W_tmp = (count <16)? sha_pad[511:480]:
        ((W[95:64]^W[255:224]^W[447:416]^W[511:480])<<1)|((W[95:64]^W[255:224]^W[447:416]^W[511:480])>>31);


    fun Fun
	(
        .B(B),
        .C(C),
        .D(D),
        .count(count),
        .res(fun_res)
	);

    k K
    (
        .count(count),
        .res(k_res)
    );

    // 状态机实现
    always @ (posedge clk) begin
        if (rst == `RstEnable) begin
            state <= STATE_IDLE;
            ready_o <= 0;
            result_o <= 160'b0;
            sha1_addr_o <= `ZeroWord;
            busy_o <= 0;

        end else begin
            case (state)
                STATE_IDLE: begin
                    if (start_i == 1) begin
                        para <= para_i;
                        sha1_addr_o <= sha1_addr_i;
                        state <= STATE_START;
                        busy_o <= `True;
                    end else begin
                        para <= `ZeroWord;
                        ready_o <= 0;
                        result_o <= 160'b0;
                        busy_o <= `False;
                        sha1_addr_o <= `ZeroWord;
                    end
                end

                STATE_START: begin
                    if (start_i == 1) begin
                        sha_pad[63:0] <= 64'd32;
                        sha_pad[511:480] <= para;
                        sha_pad[478:64] <= 415'd0;
                        sha_pad[479] <= 1;
                        A <= 32'h67452301;
                        B <= 32'hEFCDAB89;
                        C <= 32'h98BADCFE;
                        D <= 32'h10325476;
                        E <= 32'hC3D2E1F0;
                        count <=0;
                        busy_o <= 1;
                        state <= STATE_CALC;
                    end else begin
                        state <= STATE_IDLE;
                        ready_o <= 0;
                        result_o <= 160'b0;
                        busy_o <= `False;
                    end
                end

                STATE_CALC: begin
                    if (start_i == `DivStart) begin
                        count <= count+1;
                        W <= {W[479:0], W_tmp};//左移W
                        sha_pad <= {sha_pad[479:0], 32'b0}; //左移sha_pad以满足count<16时W的补充
                        if(count == 32'd79) begin
                            state <= STATE_END; 
                        end else begin
                            state <= STATE_CALC; 
                        end
                        E <= D;
                        D <= C;
                        C <= ((B<<30)|(B>>2));
                        B <= A;
                        A <= ((A<<5)|(A>>(32-5))) + E + fun_res + W_tmp + k_res;
                    end else begin
                        state <= STATE_IDLE;
                        ready_o <= 0;
                        result_o <= 160'b0;
                        busy_o <= `False;
                    end
                end

                STATE_END: begin
                    if (start_i == `DivStart) begin
                        ready_o <= 1;
                        state <= STATE_IDLE;
                        busy_o <= 0;
                        result_o[159:128] <= A+32'h67452301;
                        result_o[127:96] <= B+32'hEFCDAB89;
                        result_o[95:64] <= C+32'h98BADCFE;
                        result_o[63:32] <= D+32'h10325476;
                        result_o[31:0] <= E+32'hC3D2E1F0;
                    end else begin
                        state <= STATE_IDLE;
                        ready_o <= 0;
                        result_o <= 160'b0;
                        busy_o <= `False;
                    end
                end
            endcase
        end
    end
endmodule


module fun(
    input wire[31:0] B,
    input wire[31:0] C,
    input wire[31:0] D,
    input wire[31:0] count,
    output reg[31:0] res
    );

    always @ (*) begin
        if (count < 32'd20) begin
            res <= ((B&C)|((~B) & D));
        end else begin
            if (count < 32'd60 && count >= 32'd40) begin
                res <= ((B&C)|(B&D)|(C&D));
            end else begin
                res <= (B^C^D);
            end
        end
    end
endmodule

module k(
    input wire[31:0] count,
    output reg[31:0] res
    );

    always @ (*) begin
        if (count < 32'd20) begin
            res <= 32'h5A827999;
        end else begin
            if (count < 32'd40) begin
                res <= 32'h6ED9EBA1;
            end else begin
                if(count <32'd60) begin
                    res <= 32'h8F1BBCDC;
                end else begin
                    res <= 32'hCA62C1D6;
                end
            end
        end
    end
endmodule

rtl/core/sha1_dfa_tb.v
`timescale 1ns/1ns
module sha1_tb;
reg clk = 0;
reg rst = 0;
reg [31:0] in;
reg start;
reg [31:0]addr_i;
wire [159:0] out;
wire [31:0]addr_o;
wire ready;
wire busy;

sha1_dfa DUT(
	.clk(clk),
    .rst(rst),
	.para_i(in),
	.start_i(start),
    .sha1_addr_i(addr_i),
    .result_o(out),
    .ready_o(ready),
    .busy_o(busy),
    .sha1_addr_o(addr_o)
);
initial begin
    rst = 0; #30;
    rst = 1; in = 32'h31323334; start = 1; addr_i = 32'h10001000;#30; //"1234"
    in = 32'h0; addr_i = 32'h0;#3000;
	// in = 32'h41424344; #30; //"ABCD"
	// in = 32'h61626364; #30; //"abcd"
	// in = 32'h212f395e; #30; // "!/9^"
    // in = 32'h78797a61;      // "xyza"
	// in = 32'h3c3c3c3c; #30;
	// in = 32'h3d3d3d3d; #30;
	// in = 32'h3e3e3e3e; #30;
	// in = 32'h3f3f3f3f; #30;
	// in = 32'h40404040; #30;
	// in = 32'h41414141; #30;
    // in = 32'h42424242;
$stop;
#100;
$finish;
end
always begin #15 clk = ~clk; end
initial
	$monitor("At time %t, in = %x, out = %x", $time, in, out);
initial begin
	$dumpfile("sha1_dfa_test.vcd");
	$dumpvars;
end
endmodule

rtl/core/sha1_dfa_test.vcd
$date
	Tue Jan 19 01:38:29 2021
$end
$version
	Icarus Verilog
$end
$timescale
	1ns
$end
$scope module sha1_tb $end
$var wire 1 ! ready $end
$var wire 160 " out [159:0] $end
$var wire 1 # busy $end
$var wire 32 $ addr_o [31:0] $end
$var reg 32 % addr_i [31:0] $end
$var reg 1 & clk $end
$var reg 32 ' in [31:0] $end
$var reg 1 ( rst $end
$var reg 1 ) start $end
$scope module DUT $end
$var wire 1 & clk $end
$var wire 32 * para_i [31:0] $end
$var wire 1 ( rst $end
$var wire 32 + sha1_addr_i [31:0] $end
$var wire 1 ) start_i $end
$var wire 32 , k_res [31:0] $end
$var wire 32 - fun_res [31:0] $end
$var wire 32 . W_tmp [31:0] $end
$var reg 32 / A [31:0] $end
$var reg 32 0 B [31:0] $end
$var reg 32 1 C [31:0] $end
$var reg 32 2 D [31:0] $end
$var reg 32 3 E [31:0] $end
$var reg 512 4 W [511:0] $end
$var reg 1 # busy_o $end
$var reg 32 5 count [31:0] $end
$var reg 32 6 para [31:0] $end
$var reg 1 ! ready_o $end
$var reg 160 7 result_o [159:0] $end
$var reg 32 8 sha1_addr_o [31:0] $end
$var reg 513 9 sha_pad [512:0] $end
$var reg 4 : state [3:0] $end
$scope module Fun $end
$var wire 32 ; B [31:0] $end
$var wire 32 < C [31:0] $end
$var wire 32 = D [31:0] $end
$var wire 32 > count [31:0] $end
$var reg 32 ? res [31:0] $end
$upscope $end
$scope module K $end
$var wire 32 @ count [31:0] $end
$var reg 32 A res [31:0] $end
$upscope $end
$upscope $end
$upscope $end
$enddefinitions $end
#0
$dumpvars
bx A
bx @
bx ?
bx >
bx =
bx <
bx ;
bx :
bx 9
bx 8
bx 7
bx 6
bx 5
bx 4
bx 3
bx 2
bx 1
bx 0
bx /
bx .
bx -
bx ,
bx +
bx *
x)
0(
bx '
0&
bx %
bx $
x#
bx "
x!
$end
#15
0#
b0 $
b0 8
b0 "
b0 7
0!
b1 :
1&
#30
0&
b10000000000000001000000000000 %
b10000000000000001000000000000 +
1)
b110001001100100011001100110100 '
b110001001100100011001100110100 *
1(
#45
1#
b10 :
b10000000000000001000000000000 $
b10000000000000001000000000000 8
b110001001100100011001100110100 6
1&
#60
0&
b0 %
b0 +
b0 '
b0 *
#75
b1011010100000100111100110011001 ,
b1011010100000100111100110011001 A
b10011000101110101101110011111110 -
b10011000101110101101110011111110 ?
b110001001100100011001100110100 .
b100 :
b0 5
b0 >
b0 @
b11000011110100101110000111110000 3
b10000001100100101010001110110 2
b10000001100100101010001110110 =
b10011000101110101101110011111110 1
b10011000101110101101110011111110 <
b11101111110011011010101110001001 0
b11101111110011011010101110001001 ;
b1100111010001010010001100000001 /
bx00110001001100100011001100110100100000000000000000000000000000000000000000000000000000000000000000000000000000000000000000000000000000000000000000000000000000000000000000000000000000000000000000000000000000000000000000000000000000000000000000000000000000000000000000000000000000000000000000000000000000000000000000000000000000000000000000000000000000000000000000000000000000000000000000000000000000000000000000000000000000000000000000000000000000000000000000000000000000000000000000000000000000000000000000100000 9
1&
#90
0&
#105
b11111011111110111111111011111110 -
b11111011111110111111111011111110 ?
b10000000000000000000000000000000 .
b11010000111001101100101111100111 /
b1100111010001010010001100000001 0
b1100111010001010010001100000001 ;
b1111011111100110110101011100010 1
b1111011111100110110101011100010 <
b10011000101110101101110011111110 2
b10011000101110101101110011111110 =
b10000001100100101010001110110 3
b10000000000000000000000000000000000000000000000000000000000000000000000000000000000000000000000000000000000000000000000000000000000000000000000000000000000000000000000000000000000000000000000000000000000000000000000000000000000000000000000000000000000000000000000000000000000000000000000000000000000000000000000000000000000000000000000000000000000000000000000000000000000000000000000000000000000000000000000000000000000000000000000000000000000000000000000000000000000000000010000000000000000000000000000000000000 9
bx00110001001100100011001100110100 4
b1 5
b1 >
b1 @
1&
#120
0&
#135
b1111011110100010110100011000000 -
b1111011110100010110100011000000 ?
b0 .
b11100010100100101000000111 /
b11010000111001101100101111100111 0
b11010000111001101100101111100111 ;
b1011001110100010100100011000000 1
b1011001110100010100100011000000 <
b1111011111100110110101011100010 2
b1111011111100110110101011100010 =
b10011000101110101101110011111110 3
b1000000000000000000000000000000000000000000000000000000000000000000000 9
bx0011000100110010001100110011010010000000000000000000000000000000 4
b10 5
b10 >
b10 @
1&
#150
0&
#165
b1011000010110010000001011000001 -
b1011000010110010000001011000001 ?
b11100000010110000000000000110111 /
b11100010100100101000000111 0
b11100010100100101000000111 ;
b11110100001110011011001011111001 1
b11110100001110011011001011111001 <
b1011001110100010100100011000000 2
b1011001110100010100100011000000 =
b1111011111100110110101011100010 3
b100000000000000000000000000000000000000000000000000000000000000000000000000000000000000000000000000000 9
bx001100010011001000110011001101001000000000000000000000000000000000000000000000000000000000000000 4
b11 5
b11 >
b11 @
1&
#180
0&
#195
b11010100011000011011001011001001 -
b11010100011000011011001011001001 ?
b111001110011101110111000111000 /
b11100000010110000000000000110111 0
b11100000010110000000000000110111 ;
b11000000111000101001001010000001 1
b11000000111000101001001010000001 <
b11110100001110011011001011111001 2
b11110100001110011011001011111001 =
b1011001110100010100100011000000 3
b10000000000000000000000000000000000000000000000000000000000000000000000000000000000000000000000000000000000000000000000000000000000000 9
bx00110001001100100011001100110100100000000000000000000000000000000000000000000000000000000000000000000000000000000000000000000000 4
b100 5
b100 >
b100 @
1&
#210
0&
#225
b11111000001001100001000010001001 -
b11111000001001100001000010001001 ?
b11000010100100110011110000101001 /
b111001110011101110111000111000 0
b111001110011101110111000111000 ;
b11111000000101100000000000001101 1
b11111000000101100000000000001101 <
b11000000111000101001001010000001 2
b11000000111000101001001010000001 =
b11110100001110011011001011111001 3
b1000000000000000000000000000000000000000000000000000000000000000000000000000000000000000000000000000000000000000000000000000000000000000000000000000000000000000000000 9
bx0011000100110010001100110011010010000000000000000000000000000000000000000000000000000000000000000000000000000000000000000000000000000000000000000000000000000000 4
b101 5
b101 >
b101 @
1&
#240
0&
#255
b111010000101110011100000001100 -
b111010000101110011100000001100 ?
b10011001010010011100001001010011 /
b11000010100100110011110000101001 0
b11000010100100110011110000101001 ;
b1110011100111011101110001110 1
b1110011100111011101110001110 <
b11111000000101100000000000001101 2
b11111000000101100000000000001101 =
b11000000111000101001001010000001 3
b100000000000000000000000000000000000000000000000000000000000000000000000000000000000000000000000000000000000000000000000000000000000000000000000000000000000000000000000000000000000000000000000000000 9
bx001100010011001000110011001101001000000000000000000000000000000000000000000000000000000000000000000000000000000000000000000000000000000000000000000000000000000000000000000000000000000000000000 4
b110 5
b110 >
b110 @
1&
#270
0&
#285
b10110001100101111101110001110 -
b10110001100101111101110001110 ?
b1111110101101001000111010011001 /
b10011001010010011100001001010011 0
b10011001010010011100001001010011 ;
b1110000101001001100111100001010 1
b1110000101001001100111100001010 <
b1110011100111011101110001110 2
b1110011100111011101110001110 =
b11111000000101100000000000001101 3
b10000000000000000000000000000000000000000000000000000000000000000000000000000000000000000000000000000000000000000000000000000000000000000000000000000000000000000000000000000000000000000000000000000000000000000000000000000000000000 9
bx00110001001100100011001100110100100000000000000000000000000000000000000000000000000000000000000000000000000000000000000000000000000000000000000000000000000000000000000000000000000000000000000000000000000000000000000000000000 4
b111 5
b111 >
b111 @
1&
#300
0&
#315
b1100110000100000100000110010010 -
b1100110000100000100000110010010 ?
b111111010111010100100001100011 /
b1111110101101001000111010011001 0
b1111110101101001000111010011001 ;
b11100110010100100111000010010100 1
b11100110010100100111000010010100 <
b1110000101001001100111100001010 2
b1110000101001001100111100001010 =
b1110011100111011101110001110 3
b1000000000000000000000000000000000000000000000000000000000000000000000000000000000000000000000000000000000000000000000000000000000000000000000000000000000000000000000000000000000000000000000000000000000000000000000000000000000000000000000000000000000000000000000 9
bx0011000100110010001100110011010010000000000000000000000000000000000000000000000000000000000000000000000000000000000000000000000000000000000000000000000000000000000000000000000000000000000000000000000000000000000000000000000000000000000000000000000000000000 4
b1000 5
b1000 >
b1000 @
1&
#330
0&
#345
b11011111000011110011000010110110 -
b11011111000011110011000010110110 ?
b10111010101011111000001100100000 /
b111111010111010100100001100011 0
b111111010111010100100001100011 ;
b1011111101011010010001110100110 1
b1011111101011010010001110100110 <
b11100110010100100111000010010100 2
b11100110010100100111000010010100 =
b1110000101001001100111100001010 3
b100000000000000000000000000000000000000000000000000000000000000000000000000000000000000000000000000000000000000000000000000000000000000000000000000000000000000000000000000000000000000000000000000000000000000000000000000000000000000000000000000000000000000000000000000000000000000000000000000000 9
bx001100010011001000110011001101001000000000000000000000000000000000000000000000000000000000000000000000000000000000000000000000000000000000000000000000000000000000000000000000000000000000000000000000000000000000000000000000000000000000000000000000000000000000000000000000000000000000000000 4
b1001 5
b1001 >
b1001 @
1&
#360
0&
#375
b11001111100001110010001010000110 -
b11001111100001110010001010000110 ?
b1001101101110101110000 /
b10111010101011111000001100100000 0
b10111010101011111000001100100000 ;
b11001111110101110101001000011000 1
b11001111110101110101001000011000 <
b1011111101011010010001110100110 2
b1011111101011010010001110100110 =
b11100110010100100111000010010100 3
b10000000000000000000000000000000000000000000000000000000000000000000000000000000000000000000000000000000000000000000000000000000000000000000000000000000000000000000000000000000000000000000000000000000000000000000000000000000000000000000000000000000000000000000000000000000000000000000000000000000000000000000000000000000000000 9
bx00110001001100100011001100110100100000000000000000000000000000000000000000000000000000000000000000000000000000000000000000000000000000000000000000000000000000000000000000000000000000000000000000000000000000000000000000000000000000000000000000000000000000000000000000000000000000000000000000000000000000000000000000000000 4
b1010 5
b1010 >
b1010 @
1&
#390
0&
#405
b11001111111100111100001001001000 -
b11001111111100111100001001001000 ?
b10101001101111011101010110011 /
b1001101101110101110000 0
b1001101101110101110000 ;
b101110101010111110000011001000 1
b101110101010111110000011001000 <
b11001111110101110101001000011000 2
b11001111110101110101001000011000 =
b1011111101011010010001110100110 3
b1000000000000000000000000000000000000000000000000000000000000000000000000000000000000000000000000000000000000000000000000000000000000000000000000000000000000000000000000000000000000000000000000000000000000000000000000000000000000000000000000000000000000000000000000000000000000000000000000000000000000000000000000000000000000000000000000000000000000000000000 9
bx0011000100110010001100110011010010000000000000000000000000000000000000000000000000000000000000000000000000000000000000000000000000000000000000000000000000000000000000000000000000000000000000000000000000000000000000000000000000000000000000000000000000000000000000000000000000000000000000000000000000000000000000000000000000000000000000000000000000000000 4
b1011 5
b1011 >
b1011 @
1&
#420
0&
#435
b101010100010011111001001011000 -
b101010100010011111001001011000 ?
b110001000110101011010111101001 /
b10101001101111011101010110011 0
b10101001101111011101010110011 ;
b10011011011101011100 1
b10011011011101011100 <
b101110101010111110000011001000 2
b101110101010111110000011001000 =
b11001111110101110101001000011000 3
b100000000000000000000000000000000000000000000000000000000000000000000000000000000000000000000000000000000000000000000000000000000000000000000000000000000000000000000000000000000000000000000000000000000000000000000000000000000000000000000000000000000000000000000000000000000000000000000000000000000000000000000000000000000000000000000000000000000000000000000000000000000000000000000000000000 9
bx001100010011001000110011001101001000000000000000000000000000000000000000000000000000000000000000000000000000000000000000000000000000000000000000000000000000000000000000000000000000000000000000000000000000000000000000000000000000000000000000000000000000000000000000000000000000000000000000000000000000000000000000000000000000000000000000000000000000000000000000000000000000000000000000 4
b1100 5
b1100 >
b1100 @
1&
#450
0&
#465
b1000010011010011010111100 -
b1000010011010011010111100 ?
b1111000001110100111101100101111 /
b110001000110101011010111101001 0
b110001000110101011010111101001 ;
b11000101010011011110111010101100 1
b11000101010011011110111010101100 <
b10011011011101011100 2
b10011011011101011100 =
b101110101010111110000011001000 3
b10000000000000000000000000000000000000000000000000000000000000000000000000000000000000000000000000000000000000000000000000000000000000000000000000000000000000000000000000000000000000000000000000000000000000000000000000000000000000000000000000000000000000000000000000000000000000000000000000000000000000000000000000000000000000000000000000000000000000000000000000000000000000000000000000000000000000000000000000000000000000 9
bx00110001001100100011001100110100100000000000000000000000000000000000000000000000000000000000000000000000000000000000000000000000000000000000000000000000000000000000000000000000000000000000000000000000000000000000000000000000000000000000000000000000000000000000000000000000000000000000000000000000000000000000000000000000000000000000000000000000000000000000000000000000000000000000000000000000000000000000000000000000 4
b1101 5
b1101 >
b1101 @
1&
#480
0&
#495
b11001101010001111010110110101010 -
b11001101010001111010110110101010 ?
b10010001100001110110011100001100 /
b1111000001110100111101100101111 0
b1111000001110100111101100101111 ;
b1001100010001101010110101111010 1
b1001100010001101010110101111010 <
b11000101010011011110111010101100 2
b11000101010011011110111010101100 =
b10011011011101011100 3
b1000000000000000000000000000000000000000000000000000000000000000000000000000000000000000000000000000000000000000000000000000000000000000000000000000000000000000000000000000000000000000000000000000000000000000000000000000000000000000000000000000000000000000000000000000000000000000000000000000000000000000000000000000000000000000000000000000000000000000000000000000000000000000000000000000000000000000000000000000000000000000000000000000000000000000000000 9
bx0011000100110010001100110011010010000000000000000000000000000000000000000000000000000000000000000000000000000000000000000000000000000000000000000000000000000000000000000000000000000000000000000000000000000000000000000000000000000000000000000000000000000000000000000000000000000000000000000000000000000000000000000000000000000000000000000000000000000000000000000000000000000000000000000000000000000000000000000000000000000000000000000000000000000000 4
b1110 5
b1110 >
b1110 @
1&
#510
0&
#525
b11011100010001101000111001111010 -
b11011100010001101000111001111010 ?
b100000 .
b1011000110000001100000000110001 /
b10010001100001110110011100001100 0
b10010001100001110110011100001100 ;
b11011110000011101001111011001011 1
b11011110000011101001111011001011 <
b1001100010001101010110101111010 2
b1001100010001101010110101111010 =
b11000101010011011110111010101100 3
b100000000000000000000000000000000000000000000000000000000000000000000000000000000000000000000000000000000000000000000000000000000000000000000000000000000000000000000000000000000000000000000000000000000000000000000000000000000000000000000000000000000000000000000000000000000000000000000000000000000000000000000000000000000000000000000000000000000000000000000000000000000000000000000000000000000000000000000000000000000000000000000000000000000000000000000000000000000000000000000000000000 9
bx001100010011001000110011001101001000000000000000000000000000000000000000000000000000000000000000000000000000000000000000000000000000000000000000000000000000000000000000000000000000000000000000000000000000000000000000000000000000000000000000000000000000000000000000000000000000000000000000000000000000000000000000000000000000000000000000000000000000000000000000000000000000000000000000000000000000000000000000000000000000000000000000000000000000000000000000000000000000000000000000 4
b1111 5
b1111 >
b1111 @
1&
#540
0&
#555
b10000110010011101101111011001011 -
b10000110010011101101111011001011 ?
b1100010011001000110011001101000 .
b10100001011101111110100001010 /
b1011000110000001100000000110001 0
b1011000110000001100000000110001 ;
b100100011000011101100111000011 1
b100100011000011101100111000011 <
b11011110000011101001111011001011 2
b11011110000011101001111011001011 =
b1001100010001101010110101111010 3
b0 9
b110001001100100011001100110100100000000000000000000000000000000000000000000000000000000000000000000000000000000000000000000000000000000000000000000000000000000000000000000000000000000000000000000000000000000000000000000000000000000000000000000000000000000000000000000000000000000000000000000000000000000000000000000000000000000000000000000000000000000000000000000000000000000000000000000000000000000000000000000000000000000000000000000000000000000000000000000000000000000000000000000000000000000000000000100000 4
b10000 5
b10000 >
b10000 @
1&
#570
0&
#585
b110100011000010011000011001001 -
b110100011000010011000011001001 ?
b1 .
b10101010111000000110110001000 /
b10100001011101111110100001010 0
b10100001011101111110100001010 ;
b1010110001100000011000000001100 1
b1010110001100000011000000001100 <
b100100011000011101100111000011 2
b100100011000011101100111000011 =
b11011110000011101001111011001011 3
b10000000000000000000000000000000000000000000000000000000000000000000000000000000000000000000000000000000000000000000000000000000000000000000000000000000000000000000000000000000000000000000000000000000000000000000000000000000000000000000000000000000000000000000000000000000000000000000000000000000000000000000000000000000000000000000000000000000000000000000000000000000000000000000000000000000000000000000000000000000000000000000000000000000000000000000000000000000000000000010000001100010011001000110011001101000 4
b10001 5
b10001 >
b10001 @
1&
#600
0&
#615
b1000111001010000011110100000100 -
b1000111001010000011110100000100 ?
b1000000 .
b11000011100111111101000110000 /
b10101010111000000110110001000 0
b10101010111000000110110001000 ;
b10000101000010111011111101000010 1
b10000101000010111011111101000010 <
b1010110001100000011000000001100 2
b1010110001100000011000000001100 =
b100100011000011101100111000011 3
b1000000110001001100100011001100110100000000000000000000000000000000001 4
b10010 5
b10010 >
b10010 @
1&
#630
0&
#645
b10000101010110110000011101100010 -
b10000101010110110000011101100010 ?
b11000100110010001100110011010000 .
b11010100100010111101011010100011 /
b11000011100111111101000110000 0
b11000011100111111101000110000 ;
b101010101110000001101100010 1
b101010101110000001101100010 <
b10000101000010111011111101000010 2
b10000101000010111011111101000010 =
b1010110001100000011000000001100 3
b100000011000100110010001100110011010000000000000000000000000000000000100000000000000000000000001000000 4
b10011 5
b10011 >
b10011 @
1&
#660
0&
#675
b11010111110000000010101101001101 -
b11010111110000000010101101001101 ?
b1101110110110011110101110100001 ,
b1101110110110011110101110100001 A
b10 .
b10001100010100010101001001010001 /
b11010100100010111101011010100011 0
b11010100100010111101011010100011 ;
b110000111001111111010001100 1
b110000111001111111010001100 <
b101010101110000001101100010 2
b101010101110000001101100010 =
b10000101000010111011111101000010 3
b10000001100010011001000110011001101000000000000000000000000000000000010000000000000000000000000100000011000100110010001100110011010000 4
b10100 5
b10100 >
b10100 @
1&
#690
0&
#705
b1111111011011110101100101110101 -
b1111111011011110101100101110101 ?
b10000000 .
b1010101110100000010000001100011 /
b10001100010100010101001001010001 0
b10001100010100010101001001010001 ;
b11110101001000101111010110101000 1
b11110101001000101111010110101000 <
b110000111001111111010001100 2
b110000111001111111010001100 =
b101010101110000001101100010 3
b1000000110001001100100011001100110100000000000000000000000000000000001000000000000000000000000010000001100010011001000110011001101000000000000000000000000000000000010 4
b10101 5
b10101 >
b10101 @
1&
#720
0&
#735
b11000011111001101000000101011111 -
b11000011111001101000000101011111 ?
b10001001100100011001100110100001 .
b10101101101001000101010101100010 /
b1010101110100000010000001100011 0
b1010101110100000010000001100011 ;
b1100011000101000101010010010100 1
b1100011000101000101010010010100 <
b11110101001000101111010110101000 2
b11110101001000101111010110101000 =
b110000111001111111010001100 3
b100000011000100110010001100110011010000000000000000000000000000000000100000000000000000000000001000000110001001100100011001100110100000000000000000000000000000000001000000000000000000000000010000000 4
b10110 5
b10110 >
b10110 @
1&
#750
0&
#765
b11011110001000000100111101110 -
b11011110001000000100111101110 ?
b1000100 .
b1110110111110011011000110000010 /
b10101101101001000101010101100010 0
b10101101101001000101010101100010 ;
b11010101011101000000100000011000 1
b11010101011101000000100000011000 <
b1100011000101000101010010010100 2
b1100011000101000101010010010100 =
b11110101001000101111010110101000 3
b10000001100010011001000110011001101000000000000000000000000000000000010000000000000000000000000100000011000100110010001100110011010000000000000000000000000000000000100000000000000000000000001000000010001001100100011001100110100001 4
b10111 5
b10111 >
b10111 @
1&
#780
0&
#795
b1000111001001010110011000010 -
b1000111001001010110011000010 ?
b11000100110010001100110111010000 .
b1011110111101110001101111001001 /
b1110110111110011011000110000010 0
b1110110111110011011000110000010 ;
b10101011011010010001010101011000 1
b10101011011010010001010101011000 <
b11010101011101000000100000011000 2
b11010101011101000000100000011000 =
b1100011000101000101010010010100 3
b1000000110001001100100011001100110100000000000000000000000000000000001000000000000000000000000010000001100010011001000110011001101000000000000000000000000000000000010000000000000000000000000100000001000100110010001100110011010000100000000000000000000000001000100 4
b11000 5
b11000 >
b11000 @
1&
#810
0&
#825
b1101000001000000110001011110001 -
b1101000001000000110001011110001 ?
b10011001000110011001101000001 .
b1111110011111110011001111110010 /
b1011110111101110001101111001001 0
b1011110111101110001101111001001 ;
b10011101101111100110110001100000 1
b10011101101111100110110001100000 <
b10101011011010010001010101011000 2
b10101011011010010001010101011000 =
b11010101011101000000100000011000 3
b100000011000100110010001100110011010000000000000000000000000000000000100000000000000000000000001000000110001001100100011001100110100000000000000000000000000000000001000000000000000000000000010000000100010011001000110011001101000010000000000000000000000000100010011000100110010001100110111010000 4
b11001 5
b11001 >
b11001 @
1&
#840
0&
